fmpapi/__init__.py
fmpapi/fmp_get.py
fmpapi/fmp_set_api_key.py
fmpapi-1.0.0.dist-info/METADATA
fmpapi-1.0.0.dist-info/WHEEL
fmpapi-1.0.0.dist-info/licenses/LICENSE
fmpapi-1.0.0.dist-info/RECORD
