Metadata-Version: 2.4
Name: fmpapi
Version: 1.0.0
Summary: Flexible Client for the 'Financial Modeling Prep' API
Project-URL: Repository, https://github.com/tidy-finance/py-fmpapi
Project-URL: Issues, https://github.com/tidy-finance/py-fmpapi/issues
Project-URL: Changelog, https://github.com/tidy-finance/py-fmpapi/blob/master/CHANGELOG.md
Author-email: Christoph Scheuch <christoph@tidy-intelligence.com>
License: # MIT License
License-File: LICENSE
Requires-Python: >=3.10
Requires-Dist: httpx>=0.28.1
Requires-Dist: polars>=1.0.0
Provides-Extra: pandas
Requires-Dist: pandas; extra == 'pandas'
Requires-Dist: pyarrow; extra == 'pandas'
